odoo/addons/l10n_it_declaration_of_intent/README.rst
odoo/addons/l10n_it_declaration_of_intent/__init__.py
odoo/addons/l10n_it_declaration_of_intent/__manifest__.py
odoo/addons/l10n_it_declaration_of_intent/data/sequence.xml
odoo/addons/l10n_it_declaration_of_intent/demo/declaration_of_intent.xml
odoo/addons/l10n_it_declaration_of_intent/i18n/it.po
odoo/addons/l10n_it_declaration_of_intent/i18n/l10n_it_declaration_of_intent.pot
odoo/addons/l10n_it_declaration_of_intent/models/__init__.py
odoo/addons/l10n_it_declaration_of_intent/models/account.py
odoo/addons/l10n_it_declaration_of_intent/models/account_move.py
odoo/addons/l10n_it_declaration_of_intent/models/company.py
odoo/addons/l10n_it_declaration_of_intent/models/declaration.py
odoo/addons/l10n_it_declaration_of_intent/models/sale.py
odoo/addons/l10n_it_declaration_of_intent/readme/CONFIGURE.md
odoo/addons/l10n_it_declaration_of_intent/readme/CONTRIBUTORS.md
odoo/addons/l10n_it_declaration_of_intent/readme/DESCRIPTION.md
odoo/addons/l10n_it_declaration_of_intent/readme/ROADMAP.md
odoo/addons/l10n_it_declaration_of_intent/readme/USAGE.md
odoo/addons/l10n_it_declaration_of_intent/security/declaration_security.xml
odoo/addons/l10n_it_declaration_of_intent/security/ir.model.access.csv
odoo/addons/l10n_it_declaration_of_intent/static/description/icon.png
odoo/addons/l10n_it_declaration_of_intent/static/description/index.html
odoo/addons/l10n_it_declaration_of_intent/tests/__init__.py
odoo/addons/l10n_it_declaration_of_intent/tests/test_account.py
odoo/addons/l10n_it_declaration_of_intent/tests/test_declaration_of_intent.py
odoo/addons/l10n_it_declaration_of_intent/views/account_invoice_view.xml
odoo/addons/l10n_it_declaration_of_intent/views/account_view.xml
odoo/addons/l10n_it_declaration_of_intent/views/company_view.xml
odoo/addons/l10n_it_declaration_of_intent/views/declaration_of_intent_view.xml
odoo/addons/l10n_it_declaration_of_intent/wizard/__init__.py
odoo_addon_l10n_it_declaration_of_intent-16.0.1.1.1.dist-info/METADATA
odoo_addon_l10n_it_declaration_of_intent-16.0.1.1.1.dist-info/WHEEL
odoo_addon_l10n_it_declaration_of_intent-16.0.1.1.1.dist-info/top_level.txt
odoo_addon_l10n_it_declaration_of_intent-16.0.1.1.1.dist-info/RECORD
