Metadata-Version: 2.1
Name: odoo-addon-l10n_it_declaration_of_intent
Version: 16.0.1.1.1
Requires-Python: >=3.10
Requires-Dist: odoo>=16.0a,<16.1dev
Summary: Gestione dichiarazioni di intento
Home-page: https://github.com/OCA/l10n-italy
License: AGPL-3
Author: Francesco Apruzzese, Sergio Corato, Glauco Prina, Lara Baggio, Odoo Community Association (OCA)
Author-email: support@odoo-community.org
Classifier: Programming Language :: Python
Classifier: Framework :: Odoo
Classifier: Framework :: Odoo :: 16.0
Classifier: License :: OSI Approved :: GNU Affero General Public License v3
